[
  {
    "type": "Student",
    "fio": "Петрова Анна Сергеевна",
    "birthdate": "2005-08-20",
    "group": "БИВТ-25-1",
    "gpa": 4.9,
    "status": "Активный",
    "specialization": null,
    "has_thesis": null,
    "research_area": null,
    "supervisor": null,
    "papers_count": null
  },
  {
    "type": "Student",
    "fio": "Морозов Артем Сергеевич",
    "birthdate": "2005-12-18",
    "group": "БИВТ-25-2",
    "gpa": 3.5,
    "status": "Активный",
    "specialization": null,
    "has_thesis": null,
    "research_area": null,
    "supervisor": null,
    "papers_count": null
  },
  {
    "type": "BachelorStudent",
    "fio": "Козлова Екатерина Дмитриевна",
    "birthdate": "2004-11-25",
    "group": "БИВТ-24-2",
    "gpa": 4.8,
    "status": "Активный",
    "specialization": "Искусственный интеллект",
    "has_thesis": true,
    "research_area": null,
    "supervisor": null,
    "papers_count": null
  },
  {
    "type": "Student",
    "fio": "Иванов Иван Иванович",
    "birthdate": "2005-05-15",
    "group": "БИВТ-25-1",
    "gpa": 4.7,
    "status": "Активный",
    "specialization": null,
    "has_thesis": null,
    "research_area": null,
    "supervisor": null,
    "papers_count": null
  },
  {
    "type": "BachelorStudent",
    "fio": "Новикова Наталья Николаевна",
    "birthdate": "2004-09-12",
    "group": "БИВТ-24-1",
    "gpa": 4.4,
    "status": "Активный",
    "specialization": "Веб-технологии",
    "has_thesis": false,
    "research_area": null,
    "supervisor": null,
    "papers_count": null
  },
  {
    "type": "Student",
    "fio": "Егорова Елена Егоровна",
    "birthdate": "2005-04-08",
    "group": "БИВТ-25-2",
    "gpa": 4.1,
    "status": "Активный",
    "specialization": null,
    "has_thesis": null,
    "research_area": null,
    "supervisor": null,
    "papers_count": null
  },
  {
    "type": "BachelorStudent",
    "fio": "Сидоров Алексей Владимирович",
    "birthdate": "2004-03-10",
    "group": "БИВТ-24-1",
    "gpa": 4.2,
    "status": "Активный",
    "specialization": "Программная инженерия",
    "has_thesis": false,
    "research_area": null,
    "supervisor": null,
    "papers_count": null
  },
  {
    "type": "MasterStudent",
    "fio": "Смирнов Дмитрий Алексеевич",
    "birthdate": "2002-07-05",
    "group": "МАГ-22-1",
    "gpa": 4.9,
    "status": "Активный",
    "specialization": null,
    "has_thesis": null,
    "research_area": "Машинное обучение",
    "supervisor": "Проф. Соколов И.И.",
    "papers_count": 0
  },
  {
    "type": "MasterStudent",
    "fio": "Волкова Мария Игоревна",
    "birthdate": "2003-01-30",
    "group": "МАГ-22-1",
    "gpa": 4.7,
    "status": "Активный",
    "specialization": null,
    "has_thesis": null,
    "research_area": "Анализ данных",
    "supervisor": "Проф. Петрова А.В.",
    "papers_count": 0
  },
  {
    "type": "MasterStudent",
    "fio": "Федоров Филипп Федорович",
    "birthdate": "2001-06-22",
    "group": "МАГ-21-1",
    "gpa": 4.8,
    "status": "Активный",
    "specialization": null,
    "has_thesis": null,
    "research_area": "Кибербезопасность",
    "supervisor": "Проф. Иванов К.К.",
    "papers_count": 0
  }
]